[
   {"nrocontrol":"17420571","codigo_materia":"SADG-20"},
   {"nrocontrol":"17420571","codigo_materia":"SAIS-100"},
   {"nrocontrol":"17420571","codigo_materia":"SADG-22"},
   {"nrocontrol":"17420571","codigo_materia":"SAIS-101"},
   {"nrocontrol":"17420571","codigo_materia":"SADG-27"},
   {"nrocontrol":"17420571","codigo_materia":"SAIS-104"},

   {"nrocontrol":"17420565","codigo_materia":"SADG-20"},
   {"nrocontrol":"17420565","codigo_materia":"SAIS-100"},
   {"nrocontrol":"17420565","codigo_materia":"SADG-22"},
   {"nrocontrol":"17420565","codigo_materia":"SAIS-101"},
   {"nrocontrol":"17420565","codigo_materia":"SADG-27"},
   {"nrocontrol":"17420565","codigo_materia":"SAIS-104"},

   {"nrocontrol":"17420575","codigo_materia":"SADG-20"},
   {"nrocontrol":"17420575","codigo_materia":"SAIS-100"},
   {"nrocontrol":"17420575","codigo_materia":"SADG-22"},
   {"nrocontrol":"17420575","codigo_materia":"SAIS-101"},
   {"nrocontrol":"17420575","codigo_materia":"SADG-27"},
   {"nrocontrol":"17420575","codigo_materia":"SAIS-104"},

   {"nrocontrol":"17420578","codigo_materia":"SADG-20"},
   {"nrocontrol":"17420578","codigo_materia":"SAIS-100"},
   {"nrocontrol":"17420578","codigo_materia":"SADG-22"},
   {"nrocontrol":"17420578","codigo_materia":"SAIS-101"},
   {"nrocontrol":"17420578","codigo_materia":"SADG-27"},
   {"nrocontrol":"17420578","codigo_materia":"SAIS-104"},

   {"nrocontrol":"17420579","codigo_materia":"SADG-20"},
   {"nrocontrol":"17420579","codigo_materia":"SAIS-100"},
   {"nrocontrol":"17420579","codigo_materia":"SADG-22"},
   {"nrocontrol":"17420579","codigo_materia":"SAIS-101"},
   {"nrocontrol":"17420579","codigo_materia":"SADG-27"},
   {"nrocontrol":"17420579","codigo_materia":"SAIS-104"},

   {"nrocontrol":"17420580","codigo_materia":"SADG-20"},
   {"nrocontrol":"17420580","codigo_materia":"SAIS-100"},
   {"nrocontrol":"17420580","codigo_materia":"SADG-22"},
   {"nrocontrol":"17420580","codigo_materia":"SAIS-101"},
   {"nrocontrol":"17420580","codigo_materia":"SADG-27"},
   {"nrocontrol":"17420580","codigo_materia":"SAIS-104"},

   {"nrocontrol":"17420581","codigo_materia":"SADG-20"},
   {"nrocontrol":"17420581","codigo_materia":"SAIS-100"},
   {"nrocontrol":"17420581","codigo_materia":"SADG-22"},
   {"nrocontrol":"17420581","codigo_materia":"SAIS-101"},
   {"nrocontrol":"17420581","codigo_materia":"SADG-27"},
   {"nrocontrol":"17420581","codigo_materia":"SAIS-104"},

   {"nrocontrol":"17420583","codigo_materia":"SADG-20"},
   {"nrocontrol":"17420583","codigo_materia":"SAIS-100"},
   {"nrocontrol":"17420583","codigo_materia":"SADG-22"},
   {"nrocontrol":"17420583","codigo_materia":"SAIS-101"},
   {"nrocontrol":"17420583","codigo_materia":"SADG-27"},
   {"nrocontrol":"17420583","codigo_materia":"SAIS-104"},

   {"nrocontrol":"17420600","codigo_materia":"SADG-20"},
   {"nrocontrol":"17420600","codigo_materia":"SAIS-100"},
   {"nrocontrol":"17420600","codigo_materia":"SADG-22"},
   {"nrocontrol":"17420600","codigo_materia":"SAIS-101"},
   {"nrocontrol":"17420600","codigo_materia":"SADG-27"},
   {"nrocontrol":"17420600","codigo_materia":"SAIS-104"},

   {"nrocontrol":"17420572","codigo_materia":"SADG-20"},
   {"nrocontrol":"17420572","codigo_materia":"SAIS-100"},
   {"nrocontrol":"17420572","codigo_materia":"SADG-22"},
   {"nrocontrol":"17420572","codigo_materia":"SAIS-101"},
   {"nrocontrol":"17420572","codigo_materia":"SADG-27"},
   {"nrocontrol":"17420572","codigo_materia":"SAIS-104"},

   {"nrocontrol":"17420574","codigo_materia":"SADG-20"},
   {"nrocontrol":"17420574","codigo_materia":"SAIS-100"},
   {"nrocontrol":"17420574","codigo_materia":"SADG-22"},
   {"nrocontrol":"17420574","codigo_materia":"SAIS-101"},
   {"nrocontrol":"17420574","codigo_materia":"SADG-27"},
   {"nrocontrol":"17420574","codigo_materia":"SAIS-104"},

   {"nrocontrol":"17420576","codigo_materia":"SADG-20"},
   {"nrocontrol":"17420576","codigo_materia":"SAIS-100"},
   {"nrocontrol":"17420576","codigo_materia":"SADG-22"},
   {"nrocontrol":"17420576","codigo_materia":"SAIS-101"},
   {"nrocontrol":"17420576","codigo_materia":"SADG-27"},
   {"nrocontrol":"17420576","codigo_materia":"SAIS-104"},

   {"nrocontrol":"17420585","codigo_materia":"SADG-20"},
   {"nrocontrol":"17420585","codigo_materia":"SAIS-100"},
   {"nrocontrol":"17420585","codigo_materia":"SADG-22"},
   {"nrocontrol":"17420585","codigo_materia":"SAIS-101"},
   {"nrocontrol":"17420585","codigo_materia":"SADG-27"},
   {"nrocontrol":"17420585","codigo_materia":"SAIS-104"},

   {"nrocontrol":"17420586","codigo_materia":"SADG-20"},
   {"nrocontrol":"17420586","codigo_materia":"SAIS-100"},
   {"nrocontrol":"17420586","codigo_materia":"SADG-22"},
   {"nrocontrol":"17420586","codigo_materia":"SAIS-101"},
   {"nrocontrol":"17420586","codigo_materia":"SADG-27"},
   {"nrocontrol":"17420586","codigo_materia":"SAIS-104"},

   {"nrocontrol":"17420573","codigo_materia":"SADG-20"},
   {"nrocontrol":"17420573","codigo_materia":"SAIS-100"},
   {"nrocontrol":"17420573","codigo_materia":"SADG-22"},
   {"nrocontrol":"17420573","codigo_materia":"SAIS-101"},
   {"nrocontrol":"17420573","codigo_materia":"SADG-27"},
   {"nrocontrol":"17420573","codigo_materia":"SAIS-104"},

   {"nrocontrol":"17420552","codigo_materia":"SADG-20"},
   {"nrocontrol":"17420552","codigo_materia":"SAIS-100"},
   {"nrocontrol":"17420552","codigo_materia":"SADG-22"},
   {"nrocontrol":"17420552","codigo_materia":"SAIS-101"},
   {"nrocontrol":"17420552","codigo_materia":"SADG-27"},
   {"nrocontrol":"17420552","codigo_materia":"SAIS-104"},

   {"nrocontrol":"17420577","codigo_materia":"SADG-20"},
   {"nrocontrol":"17420577","codigo_materia":"SAIS-100"},
   {"nrocontrol":"17420577","codigo_materia":"SADG-22"},
   {"nrocontrol":"17420577","codigo_materia":"SAIS-101"},
   {"nrocontrol":"17420577","codigo_materia":"SADG-27"},
   {"nrocontrol":"17420577","codigo_materia":"SAIS-104"},

   {"nrocontrol":"17420582","codigo_materia":"SADG-20"},
   {"nrocontrol":"17420582","codigo_materia":"SAIS-100"},
   {"nrocontrol":"17420582","codigo_materia":"SADG-22"},
   {"nrocontrol":"17420582","codigo_materia":"SAIS-101"},
   {"nrocontrol":"17420582","codigo_materia":"SADG-27"},
   {"nrocontrol":"17420582","codigo_materia":"SAIS-104"},

   {"nrocontrol":"17420584","codigo_materia":"SADG-20"},
   {"nrocontrol":"17420584","codigo_materia":"SAIS-100"},
   {"nrocontrol":"17420584","codigo_materia":"SADG-22"},
   {"nrocontrol":"17420584","codigo_materia":"SAIS-101"},
   {"nrocontrol":"17420584","codigo_materia":"SADG-27"},
   {"nrocontrol":"17420584","codigo_materia":"SAIS-104"},

   {"nrocontrol":"17420587","codigo_materia":"SADG-20"},
   {"nrocontrol":"17420587","codigo_materia":"SAIS-100"},
   {"nrocontrol":"17420587","codigo_materia":"SADG-22"},
   {"nrocontrol":"17420587","codigo_materia":"SAIS-101"},
   {"nrocontrol":"17420587","codigo_materia":"SADG-27"},
   {"nrocontrol":"17420587","codigo_materia":"SAIS-104"},


   {"nrocontrol":"19420500","codigo_materia":"SADG-20"},
   {"nrocontrol":"19420500","codigo_materia":"SADG-23"},
   {"nrocontrol":"19420500","codigo_materia":"SADG-25"},

   {"nrocontrol":"19420501","codigo_materia":"SADG-20"},
   {"nrocontrol":"19420501","codigo_materia":"SADG-23"},
   {"nrocontrol":"19420501","codigo_materia":"SADG-25"},

   {"nrocontrol":"19420502","codigo_materia":"SADG-20"},
   {"nrocontrol":"19420502","codigo_materia":"SADG-23"},
   {"nrocontrol":"19420502","codigo_materia":"SADG-25"}
]
